cf_pve/__init__.py
cf_pve/cloudflare_client.py
cf_pve/commands.py
cf_pve/config.py
cf_pve/main.py
cf_pve/proxmox_client.py
cf_pve-0.1.0.dist-info/licenses/LICENSE
cf_pve-0.1.0.dist-info/METADATA
cf_pve-0.1.0.dist-info/WHEEL
cf_pve-0.1.0.dist-info/entry_points.txt
cf_pve-0.1.0.dist-info/top_level.txt
cf_pve-0.1.0.dist-info/RECORD
